pympx/__init__.py
pympx/_version.py
pympx/etl.py
pympx/exceptions.py
pympx/jupyter.py
pympx/logconfig.py
pympx/low_level_utilities.py
pympx/pympx.py
pympx/queuing.py
pympx/utils.py
pympx/validation.py
pympx/importer_scripts/Add_Time_Elements_to_Site.eimp
pympx/importer_scripts/BulkImport.eimp
pympx/importer_scripts/EmpowerImport.eimp
pympx/importer_scripts/ExportAllDimensionElements.eimp
pympx/importer_scripts/ExportCurrentPeriods.eimp
pympx/importer_scripts/ExportDimensionElements.eimp
pympx/importer_scripts/ExportDimensionStructure.eimp
pympx/importer_scripts/ExportFirstTwoDimensions.eimp
pympx/importer_scripts/ExportSecurity.eimp
pympx/importer_scripts/ExportSingleDimension.eimp
pympx/importer_scripts/ExportSiteData1Units.eimp
pympx/importer_scripts/ExportSiteData2Units.eimp
pympx/importer_scripts/ExportSiteData3Units.eimp
pympx/importer_scripts/ExportSiteData4Units.eimp
pympx/importer_scripts/ExportSiteData5Units.eimp
pympx/importer_scripts/ExportSiteData6Units.eimp
pympx/importer_scripts/ExportSiteData7Units.eimp
pympx/importer_scripts/ExportSiteData8Units.eimp
pympx/importer_scripts/ExportSiteDetails.eimp
pympx/importer_scripts/GetEmpowerSites.eimp
pympx/importer_scripts/ImportDimensionElements.eimp
pympx/importer_scripts/ImportDimensionFields.eimp
pympx/importer_scripts/ImportDimensionStructure.eimp
pympx/importer_scripts/ImportSecurity.eimp
pympx/importer_scripts/ImportTimeDimensionElements.eimp
pympx/importer_scripts/LoadCommentaryData.eimp
pympx/importer_scripts/LoadCommentaryText.eimp
pympx/importer_scripts/Version.eimp
PyMPX-1.2.5.dist-info/LICENSE.txt
PyMPX-1.2.5.dist-info/METADATA
PyMPX-1.2.5.dist-info/WHEEL
PyMPX-1.2.5.dist-info/eager_resources.txt
PyMPX-1.2.5.dist-info/top_level.txt
PyMPX-1.2.5.dist-info/RECORD
