Metadata-Version: 2.1
Name: PyMPX
Version: 1.2.5
Summary: Metapraxis Empower python API
Author: Metapraxis Ltd.
Author-email: pympx@metapraxis.com
Maintainer: Jonathan Adrian Treloar
License: MIT License
Project-URL: Documentation, https://api.metapraxis.com
Classifier: Programming Language :: Python :: 3
Classifier: License :: OSI Approved :: MIT License
Classifier: Development Status :: 5 - Production/Stable
Classifier: Intended Audience :: Developers
Classifier: Natural Language :: English
Classifier: Operating System :: Microsoft :: Windows
Classifier: Topic :: Database :: Database Engines/Servers
Classifier: Topic :: Office/Business :: Financial
Requires-Python: >=3
License-File: LICENSE.txt
Requires-Dist: pywin32
Requires-Dist: cryptography
Requires-Dist: pandas
Requires-Dist: packaging
